cuesplit.py
cuesplit-0.2.0.dist-info/licenses/COPYING
cuesplit-0.2.0.dist-info/METADATA
cuesplit-0.2.0.dist-info/WHEEL
cuesplit-0.2.0.dist-info/entry_points.txt
cuesplit-0.2.0.dist-info/top_level.txt
cuesplit-0.2.0.dist-info/RECORD
